breath_main/__init__.py
breath_main/__main__.py
breath_main/app.py
breath_main/home.py
breath_main/login.py
breath_main/ui.py
breath_main/breath_patient_portal/__init__.py
breath_main/breath_patient_portal/register_symptoms.py
breath_main/breath_patient_portal/symptoms_checkboxes.py
breath_main/console_application/__init__.py
breath_main/console_application/console_application.py
breath_main/data_requester/__init__.py
breath_main/data_requester/climate_request.py
breath_main/session_manager/__init__.py
breath_main/session_manager/service_constructor.py
breath_main/session_manager/session_manager.py
breath_main/session_manager/login_manager/__init__.py
breath_main/session_manager/login_manager/user_level.py
breath_main/session_manager/request_manager/__init__.py
breath_main/session_manager/request_manager/availability_handler.py
breath_main/session_manager/request_manager/execution_handler.py
breath_main/session_manager/request_manager/incoming_handler.py
breath_main/session_manager/request_manager/manager.py
breath_main/session_manager/request_manager/permission_handler.py
breath_main/session_manager/request_manager/request_handler.py
breath_main/session_manager/request_manager/response_handler.py
breath_main/session_manager/request_manager/validation_handler.py
breath_main/user/__init__.py
breath_main/user/db.py
breath_main/user/oauth.py
breath_main/user/registrar.py
breath_main-0.1.0.dist-info/METADATA
breath_main-0.1.0.dist-info/WHEEL
breath_main-0.1.0.dist-info/top_level.txt
breath_main-0.1.0.dist-info/RECORD
