Metadata-Version: 2.1
Name: breath-main
Version: 0.1.0
Summary: BReATH project aims to create a interface to visualize and get insights relating asthma and weather data
Home-page: https://gitlab.com/EltonCN/breath-brazilian-research-of-atmosphere-towards-health
Author: EltonCN, João Bonucci, Lucas Araújo, Thiago Lacerda
Author-email: elton.nascimento@students.ic.unicamp.br, j218733@dac.unicamp.br, l240106@dac.unicamp.br, t244712@dac.unicamp.br
License: MIT
Project-URL: Bug Tracker, https://gitlab.com/EltonCN/breath-brazilian-research-of-atmosphere-towards-health/issues
Project-URL: Documentation, https://gitlab.com/EltonCN/breath-brazilian-research-of-atmosphere-towards-health/-/wikis/Home
Platform: UNKNOWN
Classifier: Programming Language :: Python :: 3
Classifier: Topic :: Scientific/Engineering :: Artificial Intelligence
Classifier: Topic :: Scientific/Engineering :: Medical Science Apps.
Classifier: Topic :: Scientific/Engineering :: Visualization
Classifier: License :: OSI Approved :: MIT License
Requires-Python: >=3.8
Requires-Dist: numpy
Requires-Dist: google-api-python-client
Requires-Dist: oauth2client
Requires-Dist: breath-data
Requires-Dist: breath-api-interface
Requires-Dist: breath-ml
